[
  {
    "id": "2024-adv-p1",
    "type": "jee-advanced",
    "name": "JEE Advanced 2024 Paper 1",
    "year": "2024",
    "paperNumber": "1",
    "subjects": ["physics", "chemistry", "mathematics"],
    "createdAt": "2024-05-26T10:00:00.000Z",
    "questions": [
      {
        "id": "p2024-1-p1",
        "subject": "physics",
        "type": "single",
        "text": "Question 1",
        "options": [
          "Option 1",
          "Option 2",
          "Option 3",
          "Option 4"
        ],
        "correctOption": 0,
        "marks": 3,
        "negativeMark": -1
      },
      {
        "id": "p2024-1-p2",
        "subject": "physics",
        "type": "multiple",
        "text": "Question 2",
        "options": [
          "Option 1",
          "Option 2",
          "Option 3",
          "Option 4"
        ],
        "correctOptions": [0, 2],
        "marks": 4,
        "negativeMark": -2
      },
      {
        "id": "p2024-1-p3",
        "subject": "physics",
        "type": "integer",
        "text": "Question 3",
        "correctAnswer": 5,
        "marks": 4,
        "negativeMark": 0
      },
      {
        "id": "p2024-1-c1",
        "subject": "chemistry",
        "type": "single",
        "text": "Question 4",
        "options": [
          "Option 1",
          "Option 2",
          "Option 3",
          "Option 4"
        ],
        "correctOption": 1,
        "marks": 3,
        "negativeMark": -1
      },
      {
        "id": "p2024-1-c2",
        "subject": "chemistry",
        "type": "multiple",
        "text": "Question 5",
        "options": [
          "Option 1",
          "Option 2",
          "Option 3",
          "Option 4"
        ],
        "correctOptions": [1, 3],
        "marks": 4,
        "negativeMark": -2
      },
      {
        "id": "p2024-1-c3",
        "subject": "chemistry",
        "type": "integer",
        "text": "Question 6",
        "correctAnswer": 7,
        "marks": 4,
        "negativeMark": 0
      },
      {
        "id": "p2024-1-m1",
        "subject": "mathematics",
        "type": "single",
        "text": "Question 7",
        "options": [
          "Option 1",
          "Option 2",
          "Option 3",
          "Option 4"
        ],
        "correctOption": 2,
        "marks": 3,
        "negativeMark": -1
      },
      {
        "id": "p2024-1-m2",
        "subject": "mathematics",
        "type": "multiple",
        "text": "Question 8",
        "options": [
          "Option 1",
          "Option 2",
          "Option 3",
          "Option 4"
        ],
        "correctOptions": [0, 1, 3],
        "marks": 4,
        "negativeMark": -2
      },
      {
        "id": "p2024-1-m3",
        "subject": "mathematics",
        "type": "integer",
        "text": "Question 9",
        "correctAnswer": 3,
        "marks": 4,
        "negativeMark": 0
      }
    ]
  },
  {
    "id": "2024-adv-p2",
    "type": "jee-advanced",
    "name": "JEE Advanced 2024 Paper 2",
    "year": "2024",
    "paperNumber": "2",
    "subjects": ["physics", "chemistry", "mathematics"],
    "createdAt": "2024-05-26T14:00:00.000Z",
    "questions": [
      {
        "id": "p2024-2-p1",
        "subject": "physics",
        "type": "single",
        "text": "Question 1",
        "options": [
          "Option 1",
          "Option 2",
          "Option 3",
          "Option 4"
        ],
        "correctOption": 0,
        "marks": 3,
        "negativeMark": -1
      },
      {
        "id": "p2024-2-p2",
        "subject": "physics",
        "type": "multiple",
        "text": "Question 2",
        "options": [
          "Option 1",
          "Option 2",
          "Option 3",
          "Option 4"
        ],
        "correctOptions": [0, 2],
        "marks": 4,
        "negativeMark": -2
      },
      {
        "id": "p2024-2-p3",
        "subject": "physics",
        "type": "integer",
        "text": "Question 3",
        "correctAnswer": 5,
        "marks": 4,
        "negativeMark": 0
      }
    ]
  },
  {
    "id": "2023-adv-p1",
    "type": "jee-advanced",
    "name": "JEE Advanced 2023 Paper 1",
    "year": "2023",
    "paperNumber": "1",
    "subjects": ["physics", "chemistry", "mathematics"],
    "createdAt": "2023-06-04T10:00:00.000Z",
    "questions": []
  },
  {
    "id": "2023-adv-p2",
    "type": "jee-advanced",
    "name": "JEE Advanced 2023 Paper 2",
    "year": "2023",
    "paperNumber": "2",
    "subjects": ["physics", "chemistry", "mathematics"],
    "createdAt": "2023-06-04T14:00:00.000Z",
    "questions": []
  },
  {
    "id": "2022-adv-p1",
    "type": "jee-advanced",
    "name": "JEE Advanced 2022 Paper 1",
    "year": "2022",
    "paperNumber": "1",
    "subjects": ["physics", "chemistry", "mathematics"],
    "createdAt": "2022-06-26T10:00:00.000Z",
    "questions": []
  },
  {
    "id": "2022-adv-p2",
    "type": "jee-advanced",
    "name": "JEE Advanced 2022 Paper 2",
    "year": "2022",
    "paperNumber": "2",
    "subjects": ["physics", "chemistry", "mathematics"],
    "createdAt": "2022-06-26T14:00:00.000Z",
    "questions": []
  },
  {
    "id": "2021-adv-p1",
    "type": "jee-advanced",
    "name": "JEE Advanced 2021 Paper 1",
    "year": "2021",
    "paperNumber": "1",
    "subjects": ["physics", "chemistry", "mathematics"],
    "createdAt": "2021-10-03T10:00:00.000Z",
    "questions": []
  },
  {
    "id": "2021-adv-p2",
    "type": "jee-advanced",
    "name": "JEE Advanced 2021 Paper 2",
    "year": "2021",
    "paperNumber": "2",
    "subjects": ["physics", "chemistry", "mathematics"],
    "createdAt": "2021-10-03T14:00:00.000Z",
    "questions": []
  },
  {
    "id": "2020-adv-p1",
    "type": "jee-advanced",
    "name": "JEE Advanced 2020 Paper 1",
    "year": "2020",
    "paperNumber": "1",
    "subjects": ["physics", "chemistry", "mathematics"],
    "createdAt": "2020-09-27T10:00:00.000Z",
    "questions": []
  },
  {
    "id": "2020-adv-p2",
    "type": "jee-advanced",
    "name": "JEE Advanced 2020 Paper 2",
    "year": "2020",
    "paperNumber": "2",
    "subjects": ["physics", "chemistry", "mathematics"],
    "createdAt": "2020-09-27T14:00:00.000Z",
    "questions": []
  },
  {
    "id": "2019-adv-p1",
    "type": "jee-advanced",
    "name": "JEE Advanced 2019 Paper 1",
    "year": "2019",
    "paperNumber": "1",
    "subjects": ["physics", "chemistry", "mathematics"],
    "createdAt": "2019-05-27T10:00:00.000Z",
    "questions": []
  },
  {
    "id": "2019-adv-p2",
    "type": "jee-advanced",
    "name": "JEE Advanced 2019 Paper 2",
    "year": "2019",
    "paperNumber": "2",
    "subjects": ["physics", "chemistry", "mathematics"],
    "createdAt": "2019-05-27T14:00:00.000Z",
    "questions": []
  },
  {
    "id": "2018-adv-p1",
    "type": "jee-advanced",
    "name": "JEE Advanced 2018 Paper 1",
    "year": "2018",
    "paperNumber": "1",
    "subjects": ["physics", "chemistry", "mathematics"],
    "createdAt": "2018-05-20T10:00:00.000Z",
    "questions": []
  },
  {
    "id": "2018-adv-p2",
    "type": "jee-advanced",
    "name": "JEE Advanced 2018 Paper 2",
    "year": "2018",
    "paperNumber": "2",
    "subjects": ["physics", "chemistry", "mathematics"],
    "createdAt": "2018-05-20T14:00:00.000Z",
    "questions": []
  }
]